rasdapy/__init__.py
rasdapy/db_connector.py
rasdapy/query_executor.py
rasdapy/query_result.py
rasdapy/ras_oqlquery.py
rasdapy/cores/__init__.py
rasdapy/cores/core.py
rasdapy/cores/exception_factories.py
rasdapy/cores/format_utils.py
rasdapy/cores/remote_procedures.py
rasdapy/cores/request_factories.py
rasdapy/cores/surface.py
rasdapy/cores/utils.py
rasdapy/models/__init__.py
rasdapy/models/complex.py
rasdapy/models/composite_type.py
rasdapy/models/file_storage_layout.py
rasdapy/models/mdd_types.py
rasdapy/models/minterval.py
rasdapy/models/ras_gmarray.py
rasdapy/models/ras_gmarray_builder.py
rasdapy/models/ras_storage_layout.py
rasdapy/models/result_array.py
rasdapy/models/sinterval.py
rasdapy/models/tile_assigner.py
rasdapy/stubs/__init__.py
rasdapy/stubs/client_rassrvr_service_pb2.py
rasdapy/stubs/client_rassrvr_service_pb2_grpc.py
rasdapy/stubs/common_service_pb2.py
rasdapy/stubs/common_service_pb2_grpc.py
rasdapy/stubs/rasmgr_client_service_pb2.py
rasdapy/stubs/rasmgr_client_service_pb2_grpc.py
rasdapy3-1.1.0.dist-info/LICENSE.txt
rasdapy3-1.1.0.dist-info/METADATA
rasdapy3-1.1.0.dist-info/WHEEL
rasdapy3-1.1.0.dist-info/entry_points.txt
rasdapy3-1.1.0.dist-info/top_level.txt
rasdapy3-1.1.0.dist-info/RECORD
