Metadata-Version: 2.1
Name: rasdapy3
Version: 1.1.0
Summary: Python3 interface to rasdaman
Home-page: https://rasdaman.org/browser/applications/rasdapy3
Author: Bang Pham Huu
Author-email: b.phamhuu@jacobs-university.de
License: LGPL
Project-URL: Homepage, https://rasdaman.org/browser/applications/rasdapy3
Keywords: rasdaman client api interface python
Platform: UNKNOWN
Classifier: Development Status :: 4 - Beta
Classifier: Intended Audience :: Developers
Classifier: Topic :: Software Development :: Libraries
Classifier: License :: OSI Approved :: GNU Library or Lesser General Public License (LGPL)
Classifier: Programming Language :: Python :: 3.6
Classifier: Programming Language :: Python :: 3.7
Classifier: Programming Language :: Python :: 3.8
Classifier: Programming Language :: Python :: 3.9
Classifier: Programming Language :: Python :: 3.10
License-File: LICENSE.txt
Requires-Dist: grpcio (>=1.0.0)
Requires-Dist: numpy (>=1.7.1)
Requires-Dist: protobuf (>=3.0.0)
Provides-Extra: dev
Requires-Dist: check-manifest ; extra == 'dev'
Provides-Extra: test
Requires-Dist: coverage ; extra == 'test'
